oidn/__init__.py
oidn/capi.py
oidn/constants.py
oidn/lib.linux.x64/libOpenImageDenoise.so.1.4.3
oidn/lib.linux.x64/libtbb.so.12.5
oidn-0.2.1.dist-info/LICENSE
oidn-0.2.1.dist-info/METADATA
oidn-0.2.1.dist-info/WHEEL
oidn-0.2.1.dist-info/top_level.txt
oidn-0.2.1.dist-info/RECORD
