Metadata-Version: 2.1
Name: oidn
Version: 0.2.1
Summary: A simple python binding for Intel OIDN
Home-page: https://github.com/sxysxy/OIDN-python
Author: HfCloud
Author-email: sxysxygm@gmail.com
License: Apache-2.0
Platform: Linux
Classifier: Intended Audience :: Developers
Classifier: Intended Audience :: Education
Classifier: Intended Audience :: Science/Research
Classifier: Topic :: Scientific/Engineering
Classifier: Topic :: Software Development
Classifier: Topic :: Software Development :: Libraries
Classifier: Topic :: Software Development :: Libraries :: Python Modules
Classifier: Programming Language :: Python :: 3
Requires-Python: >=3
License-File: LICENSE
Requires-Dist: numpy (>=1.12.0)
Requires-Dist: pillow
